no_server/__init__.py
no_server/main.py
no_server/sh_funcs.py
server/__init__.py
server/main.py
server/spherical_harmonics.py
spherical_harmonics-0.0.3.dist-info/METADATA
spherical_harmonics-0.0.3.dist-info/WHEEL
spherical_harmonics-0.0.3.dist-info/top_level.txt
spherical_harmonics-0.0.3.dist-info/RECORD
